[
    {
        "Protocol": "Both",
        "Port": "10823",
        "Name": "Main Game Port",
        "Description": "Port used for main game traffic",
        "Ref": "MainGamePort"
    },
    {
        "Protocol": "UDP",
        "Port": "10824",
        "Name": "Query Port",
        "Description": "Port used for main game traffic",
        "Ref": "QueryPort"
    },
    {
        "Protocol": "TCP",
        "Port": "8181",
        "Name": "WebUI Port",
        "Description": "Port used for main game traffic",
        "Ref": "WebUIPort"
    }
]